bankai.py
common/__init__.py
common/apt_applist.txt
common/dnf_applist.txt
common/flatpacks.txt
common/flatpacks_arch.txt
common/paru_applist.txt
common/snap_applist.txt
configs/__init__.py
configs/kde_shortcuts.kksrc
configs/alacritty/alacritty.toml
configs/fastfetch/config.jsonc
configs/fish/config.fish
configs/ghostty/config
configs/kitty/kitty.conf
configs/vencord/trans.theme.css
os_scripts/cachyos.py
bankai-1.0.5.dist-info/METADATA
bankai-1.0.5.dist-info/WHEEL
bankai-1.0.5.dist-info/entry_points.txt
bankai-1.0.5.dist-info/top_level.txt
bankai-1.0.5.dist-info/RECORD
