Metadata-Version: 2.4
Name: bankai
Version: 1.0.5
Summary: TUI to help you setup your Linux system
Requires-Python: >=3.12
Requires-Dist: rich
